airgpt/__init__.py
airgpt/__main__.py
airgpt-0.1.1.dist-info/LICENSE
airgpt-0.1.1.dist-info/METADATA
airgpt-0.1.1.dist-info/WHEEL
airgpt-0.1.1.dist-info/entry_points.txt
airgpt-0.1.1.dist-info/top_level.txt
airgpt-0.1.1.dist-info/RECORD
