Metadata-Version: 2.1
Name: airgpt
Version: 0.1.1
Summary: A command line tool empowered by AI and LLM
Author-email: Henry Wu <csharplus@gmail.com>, Jing Guo <jingguo.uci@gmail.com>, Mengting Li <mengtingli1010@gmail.com>
License: Apache License
Project-URL: Homepage, https://github.com/kp-enterprise/airgpt
Keywords: cmd,terminal,client,llm
Classifier: License :: OSI Approved :: Apache Software License
Classifier: Programming Language :: Python
Classifier: Programming Language :: Python :: 3
Requires-Python: >=3.10
License-File: LICENSE
Requires-Dist: backoff >=2.2.1
Requires-Dist: bs4 >=0.0.1
Requires-Dist: openai >=0.28.1
Requires-Dist: python-dotenv >=1.0.0
Provides-Extra: dev
Requires-Dist: pip-tools ; extra == 'dev'
Requires-Dist: pytest ; extra == 'dev'
Requires-Dist: pytest-cov ; extra == 'dev'
